.readthedocs.yml
README.md
setup.cfg
setup.py
.github/ISSUE_TEMPLATE.md
docs/Makefile
docs/conf.py
docs/index.rst
docs/requirements.txt
examples/example.py
examples/example_data.txt
examples/explicit_plot.py
synergy_file_reader/__init__.py
synergy_file_reader/_synergy_file_reader.py
synergy_file_reader/tools.py
synergy_file_reader/version.py
synergy_file_reader.egg-info/PKG-INFO
synergy_file_reader.egg-info/SOURCES.txt
synergy_file_reader.egg-info/dependency_links.txt
synergy_file_reader.egg-info/requires.txt
synergy_file_reader.egg-info/top_level.txt
tests/decomposed_results.txt
tests/different_format.txt
tests/multiple_with_gain.txt
tests/spectrum.txt
tests/test_internals.py
tests/test_plot.py
tests/test_synergy_file.py
tests/test_tools.py
tests/multiple_observables/column.txt
tests/multiple_observables/matrix.txt
tests/multiple_observables/rowwise.txt
tests/multiple_observables/semicolon.txt
tests/sample_types/colwise.txt
tests/sample_types/colwise_noconc.txt
tests/sample_types/matrix.txt
tests/sample_types/matrix_noconc.txt
tests/sample_types/rowwise.txt
tests/sample_types/rowwise_noconc.txt
tests/sample_types/single_col.txt
tests/sample_types/single_matrix.txt
tests/sample_types/single_row.txt
tests/single_measurement/column.txt
tests/single_measurement/column_grouped.txt
tests/single_measurement/matrix.txt
tests/single_measurement/matrix_grouped.txt
tests/single_measurement/row.txt
tests/single_measurement/row_grouped.txt
tests/time_series/column_column.txt
tests/time_series/column_matrix.txt
tests/time_series/column_row.txt
tests/time_series/file_name_explanation
tests/time_series/matrix_matrix.txt
tests/time_series/row_matrix.txt